tests/__init__.py
tests/test_decrypt.py
tests/test_encrypt.py
text_encryption_decryption/__init__.py
text_encryption_decryption/decrypt.py
text_encryption_decryption/encrypt.py
text_encryption_decryption-1.0.1.dist-info/licenses/LICENSE
text_encryption_decryption-1.0.1.dist-info/METADATA
text_encryption_decryption-1.0.1.dist-info/WHEEL
text_encryption_decryption-1.0.1.dist-info/top_level.txt
text_encryption_decryption-1.0.1.dist-info/RECORD
